feature_forger/__init__.py
feature_forger/application/__init__.py
feature_forger/application/blacksmith.py
feature_forger/application/container.py
feature_forger/application/models/__init__.py
feature_forger/application/models/recipe.py
feature_forger/domain/__init__.py
feature_forger/domain/composite_task.py
feature_forger/domain/container.py
feature_forger/domain/dag_builder.py
feature_forger/domain/dataset_model_builder.py
feature_forger/domain/datasets/__init__.py
feature_forger/domain/datasets/bank.py
feature_forger/domain/entities/__init__.py
feature_forger/domain/entities/dataset.py
feature_forger/domain/entities/entity_model.py
feature_forger/domain/entities/feature.py
feature_forger/domain/entities/pipeline.py
feature_forger/domain/entity_models/__init__.py
feature_forger/domain/entity_models/account.py
feature_forger/domain/entity_models/transaction.py
feature_forger/domain/feature_validator.py
feature_forger/domain/features/__init__.py
feature_forger/domain/features/halved_rounded_amount_change.py
feature_forger/domain/features/rounded_amount_change.py
feature_forger/domain/features/rounded_amount_change_difference.py
feature_forger/domain/features/transaction_amount_change.py
feature_forger/domain/features/transaction_month.py
feature_forger/domain/features/transaction_rounded_amount_change_diff_doubled.py
feature_forger/domain/features/transaction_rounded_amount_change_diff_squared.py
feature_forger/domain/features/transaction_rounded_amount_change_doubled.py
feature_forger/domain/pipeline_builder.py
feature_forger/domain/pipeline_runner.py
feature_forger-0.1.2.dist-info/METADATA
feature_forger-0.1.2.dist-info/WHEEL
feature_forger-0.1.2.dist-info/RECORD
