Metadata-Version: 2.1
Name: feature-forger
Version: 0.1.2
Summary: A feature building framework to extend with your common features and compute on demand.
Author: iccyp
Author-email: shingle.knitter.0i@icloud.com
Requires-Python: >=3.10,<4.0
Classifier: Programming Language :: Python :: 3
Classifier: Programming Language :: Python :: 3.10
Classifier: Programming Language :: Python :: 3.11
Requires-Dist: dependency-injector (>=4.41.0,<5.0.0)
Requires-Dist: greenlet (>=2.0.2,<3.0.0)
Requires-Dist: ipython (>=8.13.2,<9.0.0)
Requires-Dist: matplotlib (>=3.7.1,<4.0.0)
Requires-Dist: networkx (>=3.1,<4.0)
Requires-Dist: openpyxl (>=3.1.2,<4.0.0)
Requires-Dist: pandas (>=2.0.1,<3.0.0)
Requires-Dist: pandera (>=0.14.5,<0.15.0)
Requires-Dist: pillow (>=9.5.0,<10.0.0)
Requires-Dist: prefect (>=2.10.7,<3.0.0)
Requires-Dist: pydantic (>=1.10.7,<2.0.0)
Requires-Dist: pydot (>=1.4.2,<2.0.0)
